splito/__init__.py
splito/_distance_split_base.py
splito/_distribution_split.py
splito/_kmeans_split.py
splito/_max_dissimilarity_split.py
splito/_min_max_split.py
splito/_molecular_weight.py
splito/_mood_split.py
splito/_perimeter_split.py
splito/_scaffold_split.py
splito/_split.py
splito/plot.py
splito/utils.py
splito/lohi/__init__.py
splito/lohi/_lo.py
splito/simpd/__init__.py
splito/simpd/callbacks.py
splito/simpd/clusters.py
splito/simpd/descriptors.py
splito/simpd/distance.py
splito/simpd/ga.py
splito/simpd/preprocess.py
splito/simpd/problem.py
splito/simpd/simpd.py
splito/simpd/splitter.py
splito-0.1.4.dist-info/LICENSE
splito-0.1.4.dist-info/METADATA
splito-0.1.4.dist-info/WHEEL
splito-0.1.4.dist-info/top_level.txt
splito-0.1.4.dist-info/RECORD
