Metadata-Version: 2.1
Name: splito
Version: 0.1.4
Summary: Machine Learning dataset splitting for life sciences.
Author-email: Lu Zhu <lu@valencediscovery.com>, Hadrien Mary <hadrien@valencediscovery.com>, Cas Wognum <cas@valencediscovery.com>
Project-URL: Source Code, https://github.com/datamol-io/splito
Project-URL: Bug Tracker, https://github.com/datamol-io/splito/issues
Project-URL: Documentation, https://splito-docs.datamol.io/
Classifier: Development Status :: 5 - Production/Stable
Classifier: Intended Audience :: Developers
Classifier: Intended Audience :: Healthcare Industry
Classifier: Intended Audience :: Science/Research
Classifier: Topic :: Scientific/Engineering :: Artificial Intelligence
Classifier: Topic :: Scientific/Engineering :: Bio-Informatics
Classifier: Topic :: Scientific/Engineering :: Information Analysis
Classifier: Topic :: Scientific/Engineering :: Medical Science Apps.
Classifier: Natural Language :: English
Classifier: Operating System :: OS Independent
Classifier: Programming Language :: Python
Classifier: Programming Language :: Python :: 3
Classifier: Programming Language :: Python :: 3.10
Classifier: Programming Language :: Python :: 3.11
Requires-Python: >=3.9
License-File: LICENSE
Requires-Dist: tqdm
Requires-Dist: loguru
Requires-Dist: pydantic
Requires-Dist: numpy
Requires-Dist: pandas
Requires-Dist: scipy
Requires-Dist: scikit-learn
Requires-Dist: matplotlib
Requires-Dist: seaborn
Requires-Dist: jenkspy
Requires-Dist: datamol >=0.12.5
Requires-Dist: rdkit
